8-bit_ALU/8bit_alu.v
module alu_8bit(a,b,sel,res);
    input [7:0] a, b;
    input [2:0] sel;
    output [15:0] res;

    parameter   ADD = 3'b000, 
                SUB = 3'b001,
                MUL = 3'b010,
                DIV = 3'b011,
                AND = 3'b100,
                OR  = 3'b101,
                NEG = 3'b110,
                XOR = 3'b111;
    
    reg [15:0] out;

    always @(*) begin
        case(sel)
            ADD : out = a + b;
            SUB : out = a - b;
            MUL : out = a * b;
            DIV : begin
                if(b!=0) out = a / b;
                else out = 16'h0000;
            end
            AND : out = a & b;
            OR  : out = a | b;
            NEG : out = ~a;
            XOR : out = a ^ b;
        endcase
    end
    assign res = out;


endmodule

8-bit_ALU/8bit_alu_tb.v
module alu_8bit_tb;
    reg [7:0] A, B;
    reg [2:0] SEL;
    wire [15:0] RES;

    alu_8bit UUT(.a(A), .b(B), .sel(SEL), .res(RES));
    parameter   ADD = 3'b000, 
                SUB = 3'b001,
                MUL = 3'b010,
                DIV = 3'b011,
                AND = 3'b100,
                OR  = 3'b101,
                NEG = 3'b110,
                XOR = 3'b111;

    initial begin
        $monitor("A=%b, B=%b, SEL=%b, RES=%b",A, B, SEL, RES);
        A=2; B=3; SEL=ADD; #10;
        A=3; B=2; SEL=SUB; #10;
        A=2; B=3; SEL=MUL; #10;
        A=2; B=3; SEL=DIV; #10;
        A=3; B=0; SEL=DIV; #10;
        A=2; B=3; SEL=AND; #10;
        A=2; B=3; SEL= OR;  #10;
        A=2; B=3; SEL=NEG; #10;
        A=2; B=3; SEL=XOR; #10;
        $finish;
    end
    initial begin
        $dumpfile("out.vcd");
        $dumpvars(0, alu_8bit_tb);
    end

endmodule

8-bit_ALU/out.vcd
$date
	Wed Sep  4 14:06:08 2024
$end
$version
	Icarus Verilog
$end
$timescale
	1s
$end
$scope module alu_8bit_tb $end
$var wire 16 ! RES [15:0] $end
$var reg 8 " A [7:0] $end
$var reg 8 # B [7:0] $end
$var reg 3 $ SEL [2:0] $end
$scope module UUT $end
$var wire 8 % a [7:0] $end
$var wire 8 & b [7:0] $end
$var wire 16 ' res [15:0] $end
$var wire 3 ( sel [2:0] $end
$var reg 16 ) out [15:0] $end
$upscope $end
$upscope $end
$enddefinitions $end
#0
$dumpvars
b101 )
b0 (
b101 '
b11 &
b10 %
b0 $
b11 #
b10 "
b101 !
$end
#10
b1 !
b1 '
b1 )
b1 $
b1 (
b10 #
b10 &
b11 "
b11 %
#20
b110 !
b110 '
b110 )
b10 $
b10 (
b11 #
b11 &
b10 "
b10 %
#30
b0 !
b0 '
b0 )
b11 $
b11 (
#40
b0 #
b0 &
b11 "
b11 %
#50
b10 !
b10 '
b10 )
b100 $
b100 (
b11 #
b11 &
b10 "
b10 %
#60
b11 !
b11 '
b11 )
b101 $
b101 (
#70
b1111111111111101 !
b1111111111111101 '
b1111111111111101 )
b110 $
b110 (
#80
b1 !
b1 '
b1 )
b111 $
b111 (
