full_adder/design.v
module oneBit_full_adder(a,b,c,sum,carry);

    input wire a, b, c;
    output wire sum, carry;

    wire w1, w2, w3;

    half_adder HA1(.a(a),.b(b),.sum(w1),.carry(w2));
    half_adder HA2(.a(w1),.b(c),.sum(sum),.carry(w3));

    or OR(carry, w2, w3);

endmodule 

module half_adder(a,b,sum,carry);
    input a, b;
    output sum, carry;
    assign sum = a^b;
    assign carry = a&b;
endmodule

full_adder/full_add_tb.v
module full_adder_tb;
    reg A, B, C;
    wire Sum, Carry;

    oneBit_full_adder UUT(
        .a(A),
        .b(B),
        .c(C),
        .sum(Sum),
        .carry(Carry)
    );

    initial begin
        $monitor("Time = %0t : A = %b, B = %b, C = %b -> Sum = %b, Carry = %b", 
                 $time, A, B, C, Sum, Carry);
        
        A = 0; B = 0; C = 0; #10;
        A = 0; B = 0; C = 1; #10;
        A = 0; B = 1; C = 0; #10;
        A = 0; B = 1; C = 1; #10;
        A = 1; B = 0; C = 0; #10;
        A = 1; B = 0; C = 1; #10;
        A = 1; B = 1; C = 0; #10;
        A = 1; B = 1; C = 1; #10;

        $finish;
    end
    initial begin
        $dumpfile("full_adder.vcd");
        $dumpvars(0, full_adder_tb);
    end

endmodule

full_adder/full_adder.vcd
$date
	Mon Sep  2 20:26:20 2024
$end
$version
	Icarus Verilog
$end
$timescale
	1s
$end
$scope module full_adder_tb $end
$var wire 1 ! Sum $end
$var wire 1 " Carry $end
$var reg 1 # A $end
$var reg 1 $ B $end
$var reg 1 % C $end
$scope module UUT $end
$var wire 1 # a $end
$var wire 1 $ b $end
$var wire 1 % c $end
$var wire 1 " carry $end
$var wire 1 & w3 $end
$var wire 1 ' w2 $end
$var wire 1 ( w1 $end
$var wire 1 ! sum $end
$scope module HA1 $end
$var wire 1 # a $end
$var wire 1 $ b $end
$var wire 1 ' carry $end
$var wire 1 ( sum $end
$upscope $end
$scope module HA2 $end
$var wire 1 ( a $end
$var wire 1 % b $end
$var wire 1 & carry $end
$var wire 1 ! sum $end
$upscope $end
$upscope $end
$upscope $end
$enddefinitions $end
#0
$dumpvars
0(
0'
0&
0%
0$
0#
0"
0!
$end
#10
1!
1%
#20
1(
0%
1$
#30
1"
0!
1&
1%
#40
0"
1!
0&
0%
0$
1#
#50
1"
0!
1&
1%
#60
0&
0(
1'
0%
1$
#70
1!
1%
